<?xml version="1.0" encoding="utf-8"?>
<!DOCTYPE hibernate-mapping PUBLIC "-//Hibernate/Hibernate Mapping DTD 3.0//EN"
"http://hibernate.sourceforge.net/hibernate-mapping-3.0.dtd">
<!-- 
    Mapping file autogenerated by MyEclipse Persistence Tools
-->
<hibernate-mapping>
    <class name="com.jsd.web.po.TvehicleInfoRecord007" table="tvehicle_info" catalog="com_jsd_rmgps30">
        <id name="vid" type="java.lang.Integer">
            <column name="vid" />
            <generator class="increment" />
        </id>
        <property name="vno" type="java.lang.String">
            <column name="vno" length="50" not-null="true" />
        </property>
        <property name="vname" type="java.lang.String">
            <column name="vname" length="50" not-null="true" />
        </property>
        <property name="engineNo" type="java.lang.String">
            <column name="engine_no" length="50" />
        </property>
        <property name="vm_id" type="java.lang.Integer">
            
        </property>
    </class>
</hibernate-mapping>
